odoo/addons/mgmtsystem_nonconformity_type/README.rst
odoo/addons/mgmtsystem_nonconformity_type/__init__.py
odoo/addons/mgmtsystem_nonconformity_type/__manifest__.py
odoo/addons/mgmtsystem_nonconformity_type/data/mgmtsystem_nonconformity_mail_data.xml
odoo/addons/mgmtsystem_nonconformity_type/i18n/es.po
odoo/addons/mgmtsystem_nonconformity_type/i18n/fr.po
odoo/addons/mgmtsystem_nonconformity_type/i18n/it.po
odoo/addons/mgmtsystem_nonconformity_type/i18n/mgmtsystem_nonconformity_type.pot
odoo/addons/mgmtsystem_nonconformity_type/models/__init__.py
odoo/addons/mgmtsystem_nonconformity_type/models/mgmtsystem_nonconformity.py
odoo/addons/mgmtsystem_nonconformity_type/readme/CONTRIBUTORS.md
odoo/addons/mgmtsystem_nonconformity_type/readme/DESCRIPTION.md
odoo/addons/mgmtsystem_nonconformity_type/readme/HISTORY.md
odoo/addons/mgmtsystem_nonconformity_type/readme/ROADMAP.md
odoo/addons/mgmtsystem_nonconformity_type/readme/USAGE.md
odoo/addons/mgmtsystem_nonconformity_type/static/description/icon.png
odoo/addons/mgmtsystem_nonconformity_type/static/description/index.html
odoo/addons/mgmtsystem_nonconformity_type/tests/__init__.py
odoo/addons/mgmtsystem_nonconformity_type/tests/test_nonconformity_type.py
odoo/addons/mgmtsystem_nonconformity_type/views/mgmtsystem_nonconformity_views.xml
odoo_addon_mgmtsystem_nonconformity_type-18.0.1.1.0.dist-info/METADATA
odoo_addon_mgmtsystem_nonconformity_type-18.0.1.1.0.dist-info/WHEEL
odoo_addon_mgmtsystem_nonconformity_type-18.0.1.1.0.dist-info/top_level.txt
odoo_addon_mgmtsystem_nonconformity_type-18.0.1.1.0.dist-info/RECORD
