Metadata-Version: 2.1
Name: odoo-addon-mgmtsystem_nonconformity_type
Version: 18.0.1.1.0
Requires-Python: >=3.10
Requires-Dist: odoo-addon-mgmtsystem==18.0.*
Requires-Dist: odoo-addon-mgmtsystem_nonconformity==18.0.*
Requires-Dist: odoo-addon-mgmtsystem_partner==18.0.*
Requires-Dist: odoo==18.0.*
Summary: Add Nonconformity classification for the root context.
Home-page: https://github.com/OCA/management-system
License: AGPL-3
Author: Associazione PNLUG - Gruppo Odoo, Odoo Community Association (OCA)
Author-email: support@odoo-community.org
Classifier: Programming Language :: Python
Classifier: Framework :: Odoo
Classifier: Framework :: Odoo :: 18.0
Classifier: License :: OSI Approved :: GNU Affero General Public License v3
Classifier: Development Status :: 4 - Beta
